{
  "schema_version": "1",
  "topics": [
    {
      "topic_id": "ap-precalculus",
      "topic_name": "AP Precalculus",
      "parent_id": "",
      "scope": [
        "AP Precalculus course framework (College Board).",
        "Valid: 2025 → (ongoing).",
        "Units 1–4 with cumulative exam weightings."
      ],
      "out_of_scope": [
        "Pre-AP / general high-school level content unless explicitly cited in CED.",
        "University-level content beyond AP expectations.",
        "Other AP subjects."
      ],
      "classification_hints": [
        "Use this root only when no more specific unit fits.",
        "Prefer specific Unit N nodes for content questions."
      ],
      "common_misconceptions": [],
      "common_misclassifications": [],
      "prerequisite_topics": [],
      "overlap_links": [],
      "essential_knowledge": [
        {
          "ek_id": "EK_root",
          "text": "Subject-wide overview and framework."
        }
      ]
    },
    {
      "topic_id": "ap-precalculus-unit01",
      "topic_name": "Unit 1: Polynomial and Rational Functions",
      "parent_id": "ap-precalculus",
      "scope": [
        "Unit 1 content as defined in AP Precalculus CED.",
        "Exam weighting: 30–40%"
      ],
      "out_of_scope": [
        "Content belonging to other AP units.",
        "Pre-AP / honors level content not cited in this unit."
      ],
      "classification_hints": [
        "Look for keywords from the unit title: Polynomial and Rational Functions."
      ],
      "common_misconceptions": [],
      "common_misclassifications": [],
      "prerequisite_topics": [],
      "overlap_links": [],
      "essential_knowledge": [
        {
          "ek_id": "EK_1.1",
          "text": "Core content and concepts for Unit 1: Polynomial and Rational Functions."
        },
        {
          "ek_id": "EK_1.2",
          "text": "Essential knowledge statements and learning objectives for Unit 1: Polynomial and Rational Functions."
        },
        {
          "ek_id": "EK_1.3",
          "text": "Assessment-relevant facts, definitions, and applications for Unit 1: Polynomial and Rational Functions."
        }
      ]
    },
    {
      "topic_id": "ap-precalculus-unit02",
      "topic_name": "Unit 2: Exponential and Logarithmic Functions",
      "parent_id": "ap-precalculus",
      "scope": [
        "Unit 2 content as defined in AP Precalculus CED.",
        "Exam weighting: 27–40%"
      ],
      "out_of_scope": [
        "Content belonging to other AP units.",
        "Pre-AP / honors level content not cited in this unit."
      ],
      "classification_hints": [
        "Look for keywords from the unit title: Exponential and Logarithmic Functions."
      ],
      "common_misconceptions": [],
      "common_misclassifications": [],
      "prerequisite_topics": [],
      "overlap_links": [],
      "essential_knowledge": [
        {
          "ek_id": "EK_2.1",
          "text": "Core content and concepts for Unit 2: Exponential and Logarithmic Functions."
        },
        {
          "ek_id": "EK_2.2",
          "text": "Essential knowledge statements and learning objectives for Unit 2: Exponential and Logarithmic Functions."
        },
        {
          "ek_id": "EK_2.3",
          "text": "Assessment-relevant facts, definitions, and applications for Unit 2: Exponential and Logarithmic Functions."
        }
      ]
    },
    {
      "topic_id": "ap-precalculus-unit03",
      "topic_name": "Unit 3: Trigonometric and Polar Functions",
      "parent_id": "ap-precalculus",
      "scope": [
        "Unit 3 content as defined in AP Precalculus CED.",
        "Exam weighting: 30–35%"
      ],
      "out_of_scope": [
        "Content belonging to other AP units.",
        "Pre-AP / honors level content not cited in this unit."
      ],
      "classification_hints": [
        "Look for keywords from the unit title: Trigonometric and Polar Functions."
      ],
      "common_misconceptions": [],
      "common_misclassifications": [],
      "prerequisite_topics": [],
      "overlap_links": [],
      "essential_knowledge": [
        {
          "ek_id": "EK_3.1",
          "text": "Core content and concepts for Unit 3: Trigonometric and Polar Functions."
        },
        {
          "ek_id": "EK_3.2",
          "text": "Essential knowledge statements and learning objectives for Unit 3: Trigonometric and Polar Functions."
        },
        {
          "ek_id": "EK_3.3",
          "text": "Assessment-relevant facts, definitions, and applications for Unit 3: Trigonometric and Polar Functions."
        }
      ]
    },
    {
      "topic_id": "ap-precalculus-unit04",
      "topic_name": "Unit 4: Functions Involving Parameters, Vectors, and Matrices",
      "parent_id": "ap-precalculus",
      "scope": [
        "Unit 4 content as defined in AP Precalculus CED.",
        "Exam weighting: not captured."
      ],
      "out_of_scope": [
        "Content belonging to other AP units.",
        "Pre-AP / honors level content not cited in this unit."
      ],
      "classification_hints": [
        "Look for keywords from the unit title: Functions Involving Parameters, Vectors, and Matrices."
      ],
      "common_misconceptions": [],
      "common_misclassifications": [],
      "prerequisite_topics": [],
      "overlap_links": [],
      "essential_knowledge": [
        {
          "ek_id": "EK_4.1",
          "text": "AP Precalculus Course and Exam Description                                                                  ﻿ V"
        },
        {
          "ek_id": "EK_4.2",
          "text": "AP Precalculus Course and Exam Description                                                   ﻿ V"
        }
      ]
    }
  ]
}